{
  "Index": 2464,
  "Start": "ঠ",
  "WordList": [
    {
      "ID": 10007016,
      "Word": "ঠি",
      "POS": "to",
      "Source": "init",
      "On": "2019-08-11T11:55:47.7736543-07:00"
    },
    {
      "ID": 10023259,
      "Word": "ঠ",
      "POS": "to",
      "Source": "init",
      "On": "2019-08-11T12:01:23.5051098-07:00"
    },
    {
      "ID": 10023260,
      "Word": "ঠং",
      "POS": "to",
      "Source": "init",
      "On": "2019-08-11T12:01:23.5101137-07:00"
    },
    {
      "ID": 10023261,
      "Word": "ঠংঠং",
      "POS": "to",
      "Source": "init",
      "On": "2019-08-11T12:01:23.5161172-07:00"
    },
    {
      "ID": 10023262,
      "Word": "ঠক",
      "POS": "to",
      "Source": "init",
      "On": "2019-08-11T12:01:23.5211236-07:00"
    },
    {
      "ID": 10023263,
      "Word": "ঠকজোচ্চোর",
      "POS": "to",
      "Source": "init",
      "On": "2019-08-11T12:01:23.5271271-07:00"
    },
    {
      "ID": 10023264,
      "Word": "ঠকঠক",
      "POS": "to",
      "Source": "init",
      "On": "2019-08-11T12:01:23.5331286-07:00"
    },
    {
      "ID": 10023265,
      "Word": "ঠকঠকানি",
      "POS": "to",
      "Source": "init",
      "On": "2019-08-11T12:01:23.5381356-07:00"
    },
    {
      "ID": 10023266,
      "Word": "ঠকঠকানো",
      "POS": "to",
      "Source": "init",
      "On": "2019-08-11T12:01:23.544136-07:00"
    },
    {
      "ID": 10023267,
      "Word": "ঠকবাজ",
      "POS": "to",
      "Source": "init",
      "On": "2019-08-11T12:01:23.5501431-07:00"
    },
    {
      "ID": 10023268,
      "Word": "ঠকবাজি",
      "POS": "to",
      "Source": "init",
      "On": "2019-08-11T12:01:23.5811619-07:00"
    },
    {
      "ID": 10023269,
      "Word": "ঠকা",
      "POS": "to",
      "Source": "init",
      "On": "2019-08-11T12:01:23.5901674-07:00"
    },
    {
      "ID": 10023270,
      "Word": "ঠকানো",
      "POS": "to",
      "Source": "init",
      "On": "2019-08-11T12:01:23.596171-07:00"
    },
    {
      "ID": 10023271,
      "Word": "ঠকামো",
      "POS": "to",
      "Source": "init",
      "On": "2019-08-11T12:01:23.6021745-07:00"
    },
    {
      "ID": 10023272,
      "Word": "ঠ-কার",
      "POS": "to",
      "Source": "init",
      "On": "2019-08-11T12:01:23.608179-07:00"
    },
    {
      "ID": 10023273,
      "Word": "ঠকাশঠকাশ",
      "POS": "to",
      "Source": "init",
      "On": "2019-08-11T12:01:23.6381992-07:00"
    },
    {
      "ID": 10023274,
      "Word": "ঠক্কর",
      "POS": "to",
      "Source": "init",
      "On": "2019-08-11T12:01:23.6442032-07:00"
    },
    {
      "ID": 10023275,
      "Word": "ঠগ",
      "POS": "to",
      "Source": "init",
      "On": "2019-08-11T12:01:23.6502073-07:00"
    },
    {
      "ID": 10023276,
      "Word": "ঠগজোচ্চোর",
      "POS": "to",
      "Source": "init",
      "On": "2019-08-11T12:01:23.6562113-07:00"
    },
    {
      "ID": 10023277,
      "Word": "ঠগি",
      "POS": "to",
      "Source": "init",
      "On": "2019-08-11T12:01:23.6622153-07:00"
    },
    {
      "ID": 10023278,
      "Word": "ঠগিনি",
      "POS": "to",
      "Source": "init",
      "On": "2019-08-11T12:01:23.6682199-07:00"
    },
    {
      "ID": 10023279,
      "Word": "ঠনঠন",
      "POS": "to",
      "Source": "init",
      "On": "2019-08-11T12:01:23.6742234-07:00"
    },
    {
      "ID": 10023280,
      "Word": "ঠনঠনে",
      "POS": "to",
      "Source": "init",
      "On": "2019-08-11T12:01:23.6802279-07:00"
    },
    {
      "ID": 10023281,
      "Word": "ঠমক",
      "POS": "to",
      "Source": "init",
      "On": "2019-08-11T12:01:23.6852303-07:00"
    },
    {
      "ID": 10023282,
      "Word": "ঠমকঠামক",
      "POS": "to",
      "Source": "init",
      "On": "2019-08-11T12:01:23.6912348-07:00"
    },
    {
      "ID": 10023283,
      "Word": "ঠসক",
      "POS": "to",
      "Source": "init",
      "On": "2019-08-11T12:01:23.6972389-07:00"
    },
    {
      "ID": 10023284,
      "Word": "ঠাউরে",
      "POS": "to",
      "Source": "init",
      "On": "2019-08-11T12:01:23.7032455-07:00"
    },
    {
      "ID": 10023285,
      "Word": "ঠাউরেছে",
      "POS": "to",
      "Source": "init",
      "On": "2019-08-11T12:01:23.7092485-07:00"
    },
    {
      "ID": 10023286,
      "Word": "ঠাওর",
      "POS": "to",
      "Source": "init",
      "On": "2019-08-11T12:01:23.715251-07:00"
    },
    {
      "ID": 10023287,
      "Word": "ঠাওরানো",
      "POS": "to",
      "Source": "init",
      "On": "2019-08-11T12:01:23.721255-07:00"
    },
    {
      "ID": 10023288,
      "Word": "ঠাঁই",
      "POS": "to",
      "Source": "init",
      "On": "2019-08-11T12:01:23.727259-07:00"
    },
    {
      "ID": 10023289,
      "Word": "ঠাকরুন",
      "POS": "to",
      "Source": "init",
      "On": "2019-08-11T12:01:23.7332661-07:00"
    },
    {
      "ID": 10023290,
      "Word": "ঠাকুমা",
      "POS": "to",
      "Source": "init",
      "On": "2019-08-11T12:01:23.7392692-07:00"
    },
    {
      "ID": 10023291,
      "Word": "ঠাকুর",
      "POS": "to",
      "Source": "init",
      "On": "2019-08-11T12:01:23.7462744-07:00"
    },
    {
      "ID": 10023292,
      "Word": "ঠাকুরজামাই",
      "POS": "to",
      "Source": "init",
      "On": "2019-08-11T12:01:23.7522784-07:00"
    },
    {
      "ID": 10023293,
      "Word": "ঠাকুরঝি",
      "POS": "to",
      "Source": "init",
      "On": "2019-08-11T12:01:23.7582824-07:00"
    },
    {
      "ID": 10023294,
      "Word": "ঠাকুরদা,",
      "POS": "to",
      "Source": "init",
      "On": "2019-08-11T12:01:23.7652882-07:00"
    },
    {
      "ID": 10023295,
      "Word": "ঠাকুরদাদা",
      "POS": "to",
      "Source": "init",
      "On": "2019-08-11T12:01:23.7712886-07:00"
    },
    {
      "ID": 10023296,
      "Word": "ঠাকুরদালান",
      "POS": "to",
      "Source": "init",
      "On": "2019-08-11T12:01:23.7772957-07:00"
    },
    {
      "ID": 10023297,
      "Word": "ঠাকুরপুজো",
      "POS": "to",
      "Source": "init",
      "On": "2019-08-11T12:01:23.7843004-07:00"
    },
    {
      "ID": 10023298,
      "Word": "ঠাকুরপূজা",
      "POS": "to",
      "Source": "init",
      "On": "2019-08-11T12:01:23.7903045-07:00"
    },
    {
      "ID": 10023299,
      "Word": "ঠাকুরপো",
      "POS": "to",
      "Source": "init",
      "On": "2019-08-11T12:01:23.7973061-07:00"
    },
    {
      "ID": 10023300,
      "Word": "ঠাকুরবাড়ি",
      "POS": "to",
      "Source": "init",
      "On": "2019-08-11T12:01:23.8043154-07:00"
    },
    {
      "ID": 10023301,
      "Word": "ঠাকুরমশাই,",
      "POS": "to",
      "Source": "init",
      "On": "2019-08-11T12:01:23.8113191-07:00"
    },
    {
      "ID": 10023302,
      "Word": "ঠাকুরমশায়",
      "POS": "to",
      "Source": "init",
      "On": "2019-08-11T12:01:23.81732-07:00"
    },
    {
      "ID": 10023303,
      "Word": "ঠাকুরমা",
      "POS": "to",
      "Source": "init",
      "On": "2019-08-11T12:01:23.8243278-07:00"
    },
    {
      "ID": 10023304,
      "Word": "ঠাকুরানি",
      "POS": "to",
      "Source": "init",
      "On": "2019-08-11T12:01:23.8313295-07:00"
    },
    {
      "ID": 10023305,
      "Word": "ঠাকুরালি",
      "POS": "to",
      "Source": "init",
      "On": "2019-08-11T12:01:23.8383362-07:00"
    },
    {
      "ID": 10023306,
      "Word": "ঠাট",
      "POS": "to",
      "Source": "init",
      "On": "2019-08-11T12:01:23.8443377-07:00"
    },
    {
      "ID": 10023307,
      "Word": "ঠাটঠমক",
      "POS": "to",
      "Source": "init",
      "On": "2019-08-11T12:01:23.851345-07:00"
    },
    {
      "ID": 10023308,
      "Word": "ঠাটবাট",
      "POS": "to",
      "Source": "init",
      "On": "2019-08-11T12:01:23.8573495-07:00"
    },
    {
      "ID": 10023309,
      "Word": "ঠাটাপড়া",
      "POS": "to",
      "Source": "init",
      "On": "2019-08-11T12:01:23.863353-07:00"
    },
    {
      "ID": 10023310,
      "Word": "ঠাট্টা",
      "POS": "to",
      "Source": "init",
      "On": "2019-08-11T12:01:23.8703593-07:00"
    },
    {
      "ID": 10023311,
      "Word": "ঠাট্টাইয়ার্কি",
      "POS": "to",
      "Source": "init",
      "On": "2019-08-11T12:01:23.8763659-07:00"
    },
    {
      "ID": 10023312,
      "Word": "ঠাট্টাতামাশা",
      "POS": "to",
      "Source": "init",
      "On": "2019-08-11T12:01:23.883368-07:00"
    },
    {
      "ID": 10023313,
      "Word": "ঠানদি,",
      "POS": "to",
      "Source": "init",
      "On": "2019-08-11T12:01:23.8893679-07:00"
    },
    {
      "ID": 10023314,
      "Word": "ঠানদিদি",
      "POS": "to",
      "Source": "init",
      "On": "2019-08-11T12:01:23.895372-07:00"
    },
    {
      "ID": 10023315,
      "Word": "ঠান্ডা",
      "POS": "to",
      "Source": "init",
      "On": "2019-08-11T12:01:23.901376-07:00"
    },
    {
      "ID": 10023316,
      "Word": "ঠান্ডাগরমি",
      "POS": "to",
      "Source": "init",
      "On": "2019-08-11T12:01:23.90738-07:00"
    },
    {
      "ID": 10023317,
      "Word": "ঠাম",
      "POS": "to",
      "Source": "init",
      "On": "2019-08-11T12:01:23.9143847-07:00"
    },
    {
      "ID": 10023318,
      "Word": "ঠাম্মা",
      "POS": "to",
      "Source": "init",
      "On": "2019-08-11T12:01:23.9213894-07:00"
    },
    {
      "ID": 10023319,
      "Word": "ঠায়",
      "POS": "to",
      "Source": "init",
      "On": "2019-08-11T12:01:23.9273935-07:00"
    },
    {
      "ID": 10023320,
      "Word": "ঠারাঠারি",
      "POS": "to",
      "Source": "init",
      "On": "2019-08-11T12:01:23.9334026-07:00"
    },
    {
      "ID": 10023321,
      "Word": "ঠারেঠোরে",
      "POS": "to",
      "Source": "init",
      "On": "2019-08-11T12:01:23.9404027-07:00"
    },
    {
      "ID": 10023322,
      "Word": "ঠাশ",
      "POS": "to",
      "Source": "init",
      "On": "2019-08-11T12:01:23.9464068-07:00"
    },
    {
      "ID": 10023325,
      "Word": "ঠাশঠাশ",
      "POS": "to",
      "Source": "init",
      "On": "2019-08-11T12:01:23.9644184-07:00"
    },
    {
      "ID": 10023326,
      "Word": "ঠাসবুনানি,",
      "POS": "to",
      "Source": "init",
      "On": "2019-08-11T12:01:23.9724237-07:00"
    },
    {
      "ID": 10023327,
      "Word": "ঠাসবুনুনি",
      "POS": "to",
      "Source": "init",
      "On": "2019-08-11T12:01:23.9784278-07:00"
    },
    {
      "ID": 10023328,
      "Word": "ঠাসবুনোট",
      "POS": "to",
      "Source": "init",
      "On": "2019-08-11T12:01:23.9854325-07:00"
    },
    {
      "ID": 10023329,
      "Word": "ঠাসা",
      "POS": "to",
      "Source": "init",
      "On": "2019-08-11T12:01:23.9914365-07:00"
    },
    {
      "ID": 10023330,
      "Word": "ঠাসাঠাসি",
      "POS": "to",
      "Source": "init",
      "On": "2019-08-11T12:01:24.0064507-07:00"
    },
    {
      "ID": 10023331,
      "Word": "ঠাহর",
      "POS": "to",
      "Source": "init",
      "On": "2019-08-11T12:01:24.0134549-07:00"
    },
    {
      "ID": 10023332,
      "Word": "ঠিক",
      "POS": "to",
      "Source": "init",
      "On": "2019-08-11T12:01:24.0334688-07:00"
    },
    {
      "ID": 10023333,
      "Word": "ঠিকঠাক",
      "POS": "to",
      "Source": "init",
      "On": "2019-08-11T12:01:24.0394713-07:00"
    },
    {
      "ID": 10023334,
      "Word": "ঠিকমতো",
      "POS": "to",
      "Source": "init",
      "On": "2019-08-11T12:01:24.0594858-07:00"
    },
    {
      "ID": 10023335,
      "Word": "ঠিকরানো,",
      "POS": "to",
      "Source": "init",
      "On": "2019-08-11T12:01:24.0674907-07:00"
    },
    {
      "ID": 10023336,
      "Word": "ঠিকরোনো",
      "POS": "to",
      "Source": "init",
      "On": "2019-08-11T12:01:24.0734916-07:00"
    },
    {
      "ID": 10023337,
      "Word": "ঠিকরে",
      "POS": "to",
      "Source": "init",
      "On": "2019-08-11T12:01:24.0804999-07:00"
    },
    {
      "ID": 10023338,
      "Word": "ঠিকা",
      "POS": "to",
      "Source": "init",
      "On": "2019-08-11T12:01:24.087501-07:00"
    },
    {
      "ID": 10023339,
      "Word": "ঠিকাদার,",
      "POS": "to",
      "Source": "init",
      "On": "2019-08-11T12:01:24.094517-07:00"
    },
    {
      "ID": 10023340,
      "Word": "ঠিকেদার",
      "POS": "to",
      "Source": "init",
      "On": "2019-08-11T12:01:24.1005129-07:00"
    },
    {
      "ID": 10023341,
      "Word": "ঠিকাদারি,",
      "POS": "to",
      "Source": "init",
      "On": "2019-08-11T12:01:24.1075145-07:00"
    },
    {
      "ID": 10023342,
      "Word": "ঠিকেদারি",
      "POS": "to",
      "Source": "init",
      "On": "2019-08-11T12:01:24.1135185-07:00"
    },
    {
      "ID": 10023343,
      "Word": "ঠিকানা",
      "POS": "to",
      "Source": "init",
      "On": "2019-08-11T12:01:24.1205232-07:00"
    },
    {
      "ID": 10023344,
      "Word": "ঠিকুজি",
      "POS": "to",
      "Source": "init",
      "On": "2019-08-11T12:01:24.127531-07:00"
    },
    {
      "ID": 10023345,
      "Word": "ঠিকুজিকুষ্ঠি",
      "POS": "to",
      "Source": "init",
      "On": "2019-08-11T12:01:24.133533-07:00"
    },
    {
      "ID": 10023346,
      "Word": "ঠিকে",
      "POS": "to",
      "Source": "init",
      "On": "2019-08-11T12:01:24.140393-07:00"
    },
    {
      "ID": 10023347,
      "Word": "ঠুং",
      "POS": "to",
      "Source": "init",
      "On": "2019-08-11T12:01:24.1473479-07:00"
    },
    {
      "ID": 10023348,
      "Word": "ঠুংঠাং",
      "POS": "to",
      "Source": "init",
      "On": "2019-08-11T12:01:24.1543562-07:00"
    },
    {
      "ID": 10023349,
      "Word": "ঠুংরি",
      "POS": "to",
      "Source": "init",
      "On": "2019-08-11T12:01:24.1613625-07:00"
    },
    {
      "ID": 10023350,
      "Word": "ঠুঁটো",
      "POS": "to",
      "Source": "init",
      "On": "2019-08-11T12:01:24.1683646-07:00"
    },
    {
      "ID": 10023351,
      "Word": "ঠুকঠুক",
      "POS": "to",
      "Source": "init",
      "On": "2019-08-11T12:01:24.176372-07:00"
    },
    {
      "ID": 10023352,
      "Word": "ঠুঙি",
      "POS": "to",
      "Source": "init",
      "On": "2019-08-11T12:01:24.1833747-07:00"
    },
    {
      "ID": 10023353,
      "Word": "ঠুনকো",
      "POS": "to",
      "Source": "init",
      "On": "2019-08-11T12:01:24.199388-07:00"
    },
    {
      "ID": 10023354,
      "Word": "ঠুনঠুন",
      "POS": "to",
      "Source": "init",
      "On": "2019-08-11T12:01:24.2063922-07:00"
    },
    {
      "ID": 10023355,
      "Word": "ঠুমকি",
      "POS": "to",
      "Source": "init",
      "On": "2019-08-11T12:01:24.2143981-07:00"
    },
    {
      "ID": 10023356,
      "Word": "ঠুলি",
      "POS": "to",
      "Source": "init",
      "On": "2019-08-11T12:01:24.2214028-07:00"
    },
    {
      "ID": 10023357,
      "Word": "ঠুসঠাস",
      "POS": "to",
      "Source": "init",
      "On": "2019-08-11T12:01:24.2294082-07:00"
    },
    {
      "ID": 10023358,
      "Word": "ঠেঁটি",
      "POS": "to",
      "Source": "init",
      "On": "2019-08-11T12:01:24.236884-07:00"
    },
    {
      "ID": 10023359,
      "Word": "ঠেক",
      "POS": "to",
      "Source": "init",
      "On": "2019-08-11T12:01:24.2438887-07:00"
    },
    {
      "ID": 10023360,
      "Word": "ঠেকনা",
      "POS": "to",
      "Source": "init",
      "On": "2019-08-11T12:01:24.2512285-07:00"
    },
    {
      "ID": 10023361,
      "Word": "ঠ্যাকনা",
      "POS": "to",
      "Source": "init",
      "On": "2019-08-11T12:01:24.2632355-07:00"
    },
    {
      "ID": 10023362,
      "Word": "ঠেকা",
      "POS": "to",
      "Source": "init",
      "On": "2019-08-11T12:01:24.2702412-07:00"
    },
    {
      "ID": 10023363,
      "Word": "ঠেকার,",
      "POS": "to",
      "Source": "init",
      "On": "2019-08-11T12:01:24.2772454-07:00"
    },
    {
      "ID": 10023364,
      "Word": "ঠেকারে",
      "POS": "to",
      "Source": "init",
      "On": "2019-08-11T12:01:24.2842471-07:00"
    },
    {
      "ID": 10023365,
      "Word": "ঠ্যাকার,",
      "POS": "to",
      "Source": "init",
      "On": "2019-08-11T12:01:24.2962926-07:00"
    },
    {
      "ID": 10023366,
      "Word": "ঠ্যাকারে",
      "POS": "to",
      "Source": "init",
      "On": "2019-08-11T12:01:24.3022997-07:00"
    },
    {
      "ID": 10023367,
      "Word": "ঠেলা",
      "POS": "to",
      "Source": "init",
      "On": "2019-08-11T12:01:24.3101788-07:00"
    },
    {
      "ID": 10023368,
      "Word": "ঠেস",
      "POS": "to",
      "Source": "init",
      "On": "2019-08-11T12:01:24.3171835-07:00"
    },
    {
      "ID": 10023369,
      "Word": "ঠেসা",
      "POS": "to",
      "Source": "init",
      "On": "2019-08-11T12:01:24.3261886-07:00"
    },
    {
      "ID": 10023370,
      "Word": "ঠেসাঠেসি",
      "POS": "to",
      "Source": "init",
      "On": "2019-08-11T12:01:24.3331928-07:00"
    },
    {
      "ID": 10023371,
      "Word": "ঠেসান",
      "POS": "to",
      "Source": "init",
      "On": "2019-08-11T12:01:24.3413295-07:00"
    },
    {
      "ID": 10023372,
      "Word": "ঠেসানো",
      "POS": "to",
      "Source": "init",
      "On": "2019-08-11T12:01:24.3554138-07:00"
    },
    {
      "ID": 10023373,
      "Word": "ঠোঁট",
      "POS": "to",
      "Source": "init",
      "On": "2019-08-11T12:01:24.3651486-07:00"
    },
    {
      "ID": 10023374,
      "Word": "ঠোঁটকাটা",
      "POS": "to",
      "Source": "init",
      "On": "2019-08-11T12:01:24.3721538-07:00"
    },
    {
      "ID": 10023375,
      "Word": "ঠোকর",
      "POS": "to",
      "Source": "init",
      "On": "2019-08-11T12:01:24.3801592-07:00"
    },
    {
      "ID": 10023376,
      "Word": "ঠোকরানো",
      "POS": "to",
      "Source": "init",
      "On": "2019-08-11T12:01:24.3881651-07:00"
    },
    {
      "ID": 10023377,
      "Word": "ঠোকা",
      "POS": "to",
      "Source": "init",
      "On": "2019-08-11T12:01:24.3971706-07:00"
    },
    {
      "ID": 10023378,
      "Word": "ঠোকাঠুকি",
      "POS": "to",
      "Source": "init",
      "On": "2019-08-11T12:01:24.4041753-07:00"
    },
    {
      "ID": 10023379,
      "Word": "ঠোক্কর",
      "POS": "to",
      "Source": "init",
      "On": "2019-08-11T12:01:24.4121807-07:00"
    },
    {
      "ID": 10023380,
      "Word": "ঠোঙা",
      "POS": "to",
      "Source": "init",
      "On": "2019-08-11T12:01:24.4200285-07:00"
    },
    {
      "ID": 10023381,
      "Word": "ঠোনা",
      "POS": "to",
      "Source": "init",
      "On": "2019-08-11T12:01:24.4350386-07:00"
    },
    {
      "ID": 10023382,
      "Word": "ঠোস",
      "POS": "to",
      "Source": "init",
      "On": "2019-08-11T12:01:24.4420413-07:00"
    },
    {
      "ID": 10023383,
      "Word": "ঠ্যাং",
      "POS": "to",
      "Source": "init",
      "On": "2019-08-11T12:01:24.4500482-07:00"
    },
    {
      "ID": 10023384,
      "Word": "ঠ্যাঁটা",
      "POS": "to",
      "Source": "init",
      "On": "2019-08-11T12:01:24.4580536-07:00"
    },
    {
      "ID": 10023385,
      "Word": "ঠ্যাকা",
      "POS": "to",
      "Source": "init",
      "On": "2019-08-11T12:01:24.4720614-07:00"
    },
    {
      "ID": 10023386,
      "Word": "ঠ্যাঙ",
      "POS": "to",
      "Source": "init",
      "On": "2019-08-11T12:01:24.4940778-07:00"
    },
    {
      "ID": 10023387,
      "Word": "ঠ্যাঙা",
      "POS": "to",
      "Source": "init",
      "On": "2019-08-11T12:01:24.5136119-07:00"
    },
    {
      "ID": 10023388,
      "Word": "ঠ্যাঙাড়ে",
      "POS": "to",
      "Source": "init",
      "On": "2019-08-11T12:01:24.5296181-07:00"
    },
    {
      "ID": 10023389,
      "Word": "ঠ্যাঙানি",
      "POS": "to",
      "Source": "init",
      "On": "2019-08-11T12:01:24.5380299-07:00"
    },
    {
      "ID": 10023390,
      "Word": "ঠ্যাঙানো",
      "POS": "to",
      "Source": "init",
      "On": "2019-08-11T12:01:24.5457751-07:00"
    },
    {
      "ID": 10023391,
      "Word": "ঠ্যালাগাড়ি",
      "POS": "to",
      "Source": "init",
      "On": "2019-08-11T12:01:24.5527787-07:00"
    },
    {
      "ID": 10036963,
      "Word": "ঠোঁট’",
      "POS": "to",
      "Source": "init",
      "On": "2019-08-11T12:08:26.0962161-07:00"
    },
    {
      "ID": 10041587,
      "Word": "ঠ্যালা",
      "POS": "to",
      "Source": "init",
      "On": "2019-08-11T12:11:27.0715057-07:00"
    },
    {
      "ID": 10062846,
      "Word": "ঠ,",
      "POS": "to",
      "Source": "init",
      "On": "2019-08-14T10:55:34.6530074-07:00"
    }
  ]
}